{"expireTime":9007200821586221000,"key":"gatsby-plugin-mdx-entire-payload-c7363ef269200d8c171a0ca3c3a5b58d-","val":{"mdast":{"type":"root","children":[{"type":"heading","depth":1,"children":[{"type":"text","value":"Images","position":{"start":{"line":2,"column":3,"offset":4},"end":{"line":2,"column":9,"offset":10},"indent":[]}}],"position":{"start":{"line":2,"column":1,"offset":2},"end":{"line":2,"column":9,"offset":10},"indent":[]}},{"type":"paragraph","children":[{"type":"text","value":"Images with captions","position":{"start":{"line":4,"column":1,"offset":14},"end":{"line":4,"column":21,"offset":34},"indent":[]}}],"position":{"start":{"line":4,"column":1,"offset":14},"end":{"line":4,"column":21,"offset":34},"indent":[]}},{"type":"jsx","value":"<figure>","position":{"start":{"line":6,"column":1,"offset":38},"end":{"line":6,"column":9,"offset":46},"indent":[]}},{"type":"paragraph","children":[{"type":"image","title":null,"url":"./nature-valley-by-redcharlie.jpg","alt":"Photo by redcharlie on Unsplash","position":{"start":{"line":8,"column":1,"offset":50},"end":{"line":8,"column":70,"offset":119},"indent":[]}}],"position":{"start":{"line":8,"column":1,"offset":50},"end":{"line":8,"column":70,"offset":119},"indent":[]}},{"type":"jsx","value":"</figure>","position":{"start":{"line":10,"column":1,"offset":123},"end":{"line":10,"column":10,"offset":132},"indent":[]}},{"type":"paragraph","children":[{"type":"text","value":"Use markdown in the image caption if you want!","position":{"start":{"line":12,"column":1,"offset":136},"end":{"line":12,"column":47,"offset":182},"indent":[]}}],"position":{"start":{"line":12,"column":1,"offset":136},"end":{"line":12,"column":47,"offset":182},"indent":[]}},{"type":"paragraph","children":[{"type":"image","title":null,"url":"./cloudy-day-by-riccardo-chiarini.jpg","alt":"Photo by Riccardo Chiarini on Unsplash","position":{"start":{"line":14,"column":1,"offset":186},"end":{"line":14,"column":81,"offset":266},"indent":[]}}],"position":{"start":{"line":14,"column":1,"offset":186},"end":{"line":14,"column":81,"offset":266},"indent":[]}},{"type":"heading","depth":1,"children":[{"type":"text","value":"This is an H1","position":{"start":{"line":16,"column":3,"offset":272},"end":{"line":16,"column":16,"offset":285},"indent":[]}}],"position":{"start":{"line":16,"column":1,"offset":270},"end":{"line":16,"column":16,"offset":285},"indent":[]}},{"type":"paragraph","children":[{"type":"text","value":"Quisque facilisis erat a dui. Nam malesuada ornare dolor. Cras gravida, diam sit amet rhoncus ornare, erat elit consectetuer erat, id egestas pede nibh eget odio. Proin tincidunt, velit vel porta elementum, magna diam molestie sapien, non aliquet massa pede eu diam. Aliquam iaculis. Fusce et ipsum et nulla tristique facilisis.","position":{"start":{"line":18,"column":1,"offset":289},"end":{"line":18,"column":329,"offset":617},"indent":[]}}],"position":{"start":{"line":18,"column":1,"offset":289},"end":{"line":18,"column":329,"offset":617},"indent":[]}},{"type":"heading","depth":2,"children":[{"type":"text","value":"This is an H2","position":{"start":{"line":20,"column":4,"offset":624},"end":{"line":20,"column":17,"offset":637},"indent":[]}}],"position":{"start":{"line":20,"column":1,"offset":621},"end":{"line":20,"column":17,"offset":637},"indent":[]}},{"type":"paragraph","children":[{"type":"text","value":"Lorem ipsum dolor sit amet, consectetuer adipiscing elit. Morbi commodo, ipsum sed pharetra gravida, orci magna rhoncus neque, id pulvinar odio lorem non turpis. Nullam sit amet enim. Suspendisse id velit vitae ligula volutpat condimentum. Aliquam erat volutpat. Sed quis velit. Nulla facilisi. Nulla libero.","position":{"start":{"line":22,"column":1,"offset":641},"end":{"line":22,"column":309,"offset":949},"indent":[]}}],"position":{"start":{"line":22,"column":1,"offset":641},"end":{"line":22,"column":309,"offset":949},"indent":[]}},{"type":"heading","depth":3,"children":[{"type":"text","value":"This is an H3","position":{"start":{"line":24,"column":5,"offset":957},"end":{"line":24,"column":18,"offset":970},"indent":[]}}],"position":{"start":{"line":24,"column":1,"offset":953},"end":{"line":24,"column":18,"offset":970},"indent":[]}},{"type":"paragraph","children":[{"type":"text","value":"Lorem ipsum dolor sit amet, consectetuer adipiscing elit. Morbi commodo, ipsum sed pharetra gravida, orci magna rhoncus neque, id pulvinar odio lorem non turpis. Nullam sit amet enim. Suspendisse id velit vitae ligula volutpat condimentum. Aliquam erat volutpat. Sed quis velit. Nulla facilisi. Nulla libero.","position":{"start":{"line":26,"column":1,"offset":974},"end":{"line":26,"column":309,"offset":1282},"indent":[]}}],"position":{"start":{"line":26,"column":1,"offset":974},"end":{"line":26,"column":309,"offset":1282},"indent":[]}},{"type":"heading","depth":4,"children":[{"type":"text","value":"This is an H4","position":{"start":{"line":28,"column":6,"offset":1291},"end":{"line":28,"column":19,"offset":1304},"indent":[]}}],"position":{"start":{"line":28,"column":1,"offset":1286},"end":{"line":28,"column":19,"offset":1304},"indent":[]}},{"type":"paragraph","children":[{"type":"text","value":"Quisque facilisis erat a dui. Nam malesuada ornare dolor. Cras gravida, diam sit amet rhoncus ornare, erat elit consectetuer erat, id egestas pede nibh eget odio. Proin tincidunt, velit vel porta elementum, magna diam molestie sapien, non aliquet massa pede eu diam. Aliquam iaculis.","position":{"start":{"line":30,"column":1,"offset":1308},"end":{"line":30,"column":284,"offset":1591},"indent":[]}}],"position":{"start":{"line":30,"column":1,"offset":1308},"end":{"line":30,"column":284,"offset":1591},"indent":[]}},{"type":"heading","depth":2,"children":[{"type":"text","value":"Quotes","position":{"start":{"line":32,"column":4,"offset":1598},"end":{"line":32,"column":10,"offset":1604},"indent":[]}}],"position":{"start":{"line":32,"column":1,"offset":1595},"end":{"line":32,"column":10,"offset":1604},"indent":[]}},{"type":"jsx","value":"<Blockquote by=\"Scott Adams\">\n  Creativity is allowing yourself to make mistakes. Design is knowing which ones\n  to keep.\n</Blockquote>","position":{"start":{"line":34,"column":1,"offset":1608},"end":{"line":37,"column":14,"offset":1746},"indent":[1,1,1]}},{"type":"heading","depth":2,"children":[{"type":"text","value":"Code","position":{"start":{"line":39,"column":4,"offset":1753},"end":{"line":39,"column":8,"offset":1757},"indent":[]}}],"position":{"start":{"line":39,"column":1,"offset":1750},"end":{"line":39,"column":8,"offset":1757},"indent":[]}},{"type":"code","lang":null,"meta":null,"value":"// Simple map\nvar map;\nfunction initMap() {\n  map = new google.maps.Map(document.getElementById('map'), {\n    center: {lat: -34.397, lng: 150.644},\n    zoom: 8\n  });\n}","position":{"start":{"line":41,"column":1,"offset":1761},"end":{"line":50,"column":4,"offset":1945},"indent":[1,1,1,1,1,1,1,1,1]}},{"type":"heading","depth":2,"children":[{"type":"text","value":"Lists","position":{"start":{"line":52,"column":4,"offset":1952},"end":{"line":52,"column":9,"offset":1957},"indent":[]}}],"position":{"start":{"line":52,"column":1,"offset":1949},"end":{"line":52,"column":9,"offset":1957},"indent":[]}},{"type":"heading","depth":3,"children":[{"type":"text","value":"Unordered Lists","position":{"start":{"line":54,"column":5,"offset":1965},"end":{"line":54,"column":20,"offset":1980},"indent":[]}}],"position":{"start":{"line":54,"column":1,"offset":1961},"end":{"line":54,"column":20,"offset":1980},"indent":[]}},{"type":"paragraph","children":[{"type":"text","value":"The HTML ","position":{"start":{"line":56,"column":1,"offset":1984},"end":{"line":56,"column":10,"offset":1993},"indent":[]}},{"type":"inlineCode","value":"<ul>","position":{"start":{"line":56,"column":10,"offset":1993},"end":{"line":56,"column":16,"offset":1999},"indent":[]}},{"type":"text","value":" element represents an unordered list of items, typically rendered as a bulleted list.","position":{"start":{"line":56,"column":16,"offset":1999},"end":{"line":56,"column":102,"offset":2085},"indent":[]}}],"position":{"start":{"line":56,"column":1,"offset":1984},"end":{"line":56,"column":102,"offset":2085},"indent":[]}},{"type":"paragraph","children":[{"type":"text","value":"Usage notes:","position":{"start":{"line":58,"column":1,"offset":2089},"end":{"line":58,"column":13,"offset":2101},"indent":[]}}],"position":{"start":{"line":58,"column":1,"offset":2089},"end":{"line":58,"column":13,"offset":2101},"indent":[]}},{"type":"list","ordered":false,"start":null,"spread":false,"children":[{"type":"listItem","spread":false,"checked":null,"children":[{"type":"paragraph","children":[{"type":"text","value":"The ","position":{"start":{"line":60,"column":3,"offset":2107},"end":{"line":60,"column":7,"offset":2111},"indent":[]}},{"type":"inlineCode","value":"<ul>","position":{"start":{"line":60,"column":7,"offset":2111},"end":{"line":60,"column":13,"offset":2117},"indent":[]}},{"type":"text","value":" element is for grouping a collection of items that do not have a numerical ordering, and their order in the list is meaningless. Typically, unordered-list items are displayed with a bullet, which can be of several forms, like a dot, a circle or a squared.","position":{"start":{"line":60,"column":13,"offset":2117},"end":{"line":60,"column":269,"offset":2373},"indent":[]}}],"position":{"start":{"line":60,"column":3,"offset":2107},"end":{"line":60,"column":269,"offset":2373},"indent":[]}}],"position":{"start":{"line":60,"column":1,"offset":2105},"end":{"line":60,"column":269,"offset":2373},"indent":[]}},{"type":"listItem","spread":false,"checked":null,"children":[{"type":"paragraph","children":[{"type":"text","value":"There is no limitation to the depth and alternation of nested lists defined with the ","position":{"start":{"line":61,"column":3,"offset":2377},"end":{"line":61,"column":88,"offset":2462},"indent":[]}},{"type":"inlineCode","value":"<ol>","position":{"start":{"line":61,"column":88,"offset":2462},"end":{"line":61,"column":94,"offset":2468},"indent":[]}},{"type":"text","value":" and ","position":{"start":{"line":61,"column":94,"offset":2468},"end":{"line":61,"column":99,"offset":2473},"indent":[]}},{"type":"inlineCode","value":"<ul>","position":{"start":{"line":61,"column":99,"offset":2473},"end":{"line":61,"column":105,"offset":2479},"indent":[]}},{"type":"text","value":" elements.","position":{"start":{"line":61,"column":105,"offset":2479},"end":{"line":61,"column":115,"offset":2489},"indent":[]}}],"position":{"start":{"line":61,"column":3,"offset":2377},"end":{"line":61,"column":115,"offset":2489},"indent":[]}}],"position":{"start":{"line":61,"column":1,"offset":2375},"end":{"line":61,"column":115,"offset":2489},"indent":[]}},{"type":"listItem","spread":false,"checked":null,"children":[{"type":"paragraph","children":[{"type":"text","value":"The ","position":{"start":{"line":62,"column":3,"offset":2493},"end":{"line":62,"column":7,"offset":2497},"indent":[]}},{"type":"inlineCode","value":"<ol>","position":{"start":{"line":62,"column":7,"offset":2497},"end":{"line":62,"column":13,"offset":2503},"indent":[]}},{"type":"text","value":" and ","position":{"start":{"line":62,"column":13,"offset":2503},"end":{"line":62,"column":18,"offset":2508},"indent":[]}},{"type":"inlineCode","value":"<ul>","position":{"start":{"line":62,"column":18,"offset":2508},"end":{"line":62,"column":24,"offset":2514},"indent":[]}},{"type":"text","value":" elements both represent a list of items. They differ in that, with the ","position":{"start":{"line":62,"column":24,"offset":2514},"end":{"line":62,"column":96,"offset":2586},"indent":[]}},{"type":"inlineCode","value":"<ol>","position":{"start":{"line":62,"column":96,"offset":2586},"end":{"line":62,"column":102,"offset":2592},"indent":[]}},{"type":"text","value":" element, the order is meaningful.","position":{"start":{"line":62,"column":102,"offset":2592},"end":{"line":62,"column":136,"offset":2626},"indent":[]}}],"position":{"start":{"line":62,"column":3,"offset":2493},"end":{"line":62,"column":136,"offset":2626},"indent":[]}}],"position":{"start":{"line":62,"column":1,"offset":2491},"end":{"line":62,"column":136,"offset":2626},"indent":[]}}],"position":{"start":{"line":60,"column":1,"offset":2105},"end":{"line":62,"column":136,"offset":2626},"indent":[1,1]}},{"type":"heading","depth":3,"children":[{"type":"text","value":"Ordered Lists","position":{"start":{"line":64,"column":5,"offset":2634},"end":{"line":64,"column":18,"offset":2647},"indent":[]}}],"position":{"start":{"line":64,"column":1,"offset":2630},"end":{"line":64,"column":18,"offset":2647},"indent":[]}},{"type":"paragraph","children":[{"type":"text","value":"The HTML ","position":{"start":{"line":66,"column":1,"offset":2651},"end":{"line":66,"column":10,"offset":2660},"indent":[]}},{"type":"inlineCode","value":"<ol>","position":{"start":{"line":66,"column":10,"offset":2660},"end":{"line":66,"column":16,"offset":2666},"indent":[]}},{"type":"text","value":" element represents an ordered list of items, typically rendered as a numbered list.","position":{"start":{"line":66,"column":16,"offset":2666},"end":{"line":66,"column":100,"offset":2750},"indent":[]}}],"position":{"start":{"line":66,"column":1,"offset":2651},"end":{"line":66,"column":100,"offset":2750},"indent":[]}},{"type":"paragraph","children":[{"type":"text","value":"Usage notes:","position":{"start":{"line":68,"column":1,"offset":2754},"end":{"line":68,"column":13,"offset":2766},"indent":[]}}],"position":{"start":{"line":68,"column":1,"offset":2754},"end":{"line":68,"column":13,"offset":2766},"indent":[]}},{"type":"list","ordered":true,"start":1,"spread":false,"children":[{"type":"listItem","spread":false,"checked":null,"children":[{"type":"paragraph","children":[{"type":"text","value":"Typically, ordered-list items are displayed with a preceding numbering, which can be of any form, like numerals, letters or Romans numerals or even simple bullets.","position":{"start":{"line":70,"column":4,"offset":2773},"end":{"line":70,"column":167,"offset":2936},"indent":[]}}],"position":{"start":{"line":70,"column":4,"offset":2773},"end":{"line":70,"column":167,"offset":2936},"indent":[]}}],"position":{"start":{"line":70,"column":1,"offset":2770},"end":{"line":70,"column":167,"offset":2936},"indent":[]}},{"type":"listItem","spread":false,"checked":null,"children":[{"type":"paragraph","children":[{"type":"text","value":"There is no limitation to the depth and alternation of nested lists defined with the ","position":{"start":{"line":71,"column":4,"offset":2941},"end":{"line":71,"column":89,"offset":3026},"indent":[]}},{"type":"inlineCode","value":"<ol>","position":{"start":{"line":71,"column":89,"offset":3026},"end":{"line":71,"column":95,"offset":3032},"indent":[]}},{"type":"text","value":" and ","position":{"start":{"line":71,"column":95,"offset":3032},"end":{"line":71,"column":100,"offset":3037},"indent":[]}},{"type":"inlineCode","value":"<ul>","position":{"start":{"line":71,"column":100,"offset":3037},"end":{"line":71,"column":106,"offset":3043},"indent":[]}},{"type":"text","value":" elements.","position":{"start":{"line":71,"column":106,"offset":3043},"end":{"line":71,"column":116,"offset":3053},"indent":[]}}],"position":{"start":{"line":71,"column":4,"offset":2941},"end":{"line":71,"column":116,"offset":3053},"indent":[]}}],"position":{"start":{"line":71,"column":1,"offset":2938},"end":{"line":71,"column":116,"offset":3053},"indent":[]}},{"type":"listItem","spread":false,"checked":null,"children":[{"type":"paragraph","children":[{"type":"text","value":"The ","position":{"start":{"line":72,"column":4,"offset":3058},"end":{"line":72,"column":8,"offset":3062},"indent":[]}},{"type":"inlineCode","value":"<ol>","position":{"start":{"line":72,"column":8,"offset":3062},"end":{"line":72,"column":14,"offset":3068},"indent":[]}},{"type":"text","value":" and ","position":{"start":{"line":72,"column":14,"offset":3068},"end":{"line":72,"column":19,"offset":3073},"indent":[]}},{"type":"inlineCode","value":"<ul>","position":{"start":{"line":72,"column":19,"offset":3073},"end":{"line":72,"column":25,"offset":3079},"indent":[]}},{"type":"text","value":" both represent a list of items. They differ in the way that, with the ","position":{"start":{"line":72,"column":25,"offset":3079},"end":{"line":72,"column":96,"offset":3150},"indent":[]}},{"type":"inlineCode","value":"<ol>","position":{"start":{"line":72,"column":96,"offset":3150},"end":{"line":72,"column":102,"offset":3156},"indent":[]}},{"type":"text","value":" element, the order is meaningful.","position":{"start":{"line":72,"column":102,"offset":3156},"end":{"line":72,"column":136,"offset":3190},"indent":[]}}],"position":{"start":{"line":72,"column":4,"offset":3058},"end":{"line":72,"column":136,"offset":3190},"indent":[]}}],"position":{"start":{"line":72,"column":1,"offset":3055},"end":{"line":72,"column":136,"offset":3190},"indent":[]}}],"position":{"start":{"line":70,"column":1,"offset":2770},"end":{"line":72,"column":136,"offset":3190},"indent":[1,1]}},{"type":"heading","depth":2,"children":[{"type":"text","value":"Videos","position":{"start":{"line":74,"column":4,"offset":3197},"end":{"line":74,"column":10,"offset":3203},"indent":[]}}],"position":{"start":{"line":74,"column":1,"offset":3194},"end":{"line":74,"column":10,"offset":3203},"indent":[]}},{"type":"jsx","value":"<Video url=\"https://www.youtube.com/watch?v=lC5lsemxaJo\" />","position":{"start":{"line":76,"column":1,"offset":3207},"end":{"line":76,"column":60,"offset":3266},"indent":[]}},{"type":"export","value":"export const _frontmatter = {\"title\":\"Testerino\",\"date\":\"2015-05-28T22:40:32.169Z\",\"description\":\"This is a custom description for SEO and Open Graph purposes, rather than the default generated excerpt. Simply add a description field to the frontmatter.\",\"featuredImage\":\"./grassland-by-qingbao-meng.jpg\"}","position":{"start":{"line":79,"column":1,"offset":3270},"end":{"line":79,"column":306,"offset":3575},"indent":[]}}],"position":{"start":{"line":1,"column":1,"offset":0},"end":{"line":79,"column":306,"offset":3575}}},"scopeImports":["import React from 'react'"],"scopeIdentifiers":["React"],"body":"function _extends() { _extends = Object.assign || function (target) { for (var i = 1; i < arguments.length; i++) { var source = arguments[i]; for (var key in source) { if (Object.prototype.hasOwnProperty.call(source, key)) { target[key] = source[key]; } } } return target; }; return _extends.apply(this, arguments); }\n\nfunction _objectWithoutProperties(source, excluded) { if (source == null) return {}; var target = _objectWithoutPropertiesLoose(source, excluded); var key, i; if (Object.getOwnPropertySymbols) { var sourceSymbolKeys = Object.getOwnPropertySymbols(source); for (i = 0; i < sourceSymbolKeys.length; i++) { key = sourceSymbolKeys[i]; if (excluded.indexOf(key) >= 0) continue; if (!Object.prototype.propertyIsEnumerable.call(source, key)) continue; target[key] = source[key]; } } return target; }\n\nfunction _objectWithoutPropertiesLoose(source, excluded) { if (source == null) return {}; var target = {}; var sourceKeys = Object.keys(source); var key, i; for (i = 0; i < sourceKeys.length; i++) { key = sourceKeys[i]; if (excluded.indexOf(key) >= 0) continue; target[key] = source[key]; } return target; }\n\n/* @jsx mdx */\nvar _frontmatter = {\n  \"title\": \"Testerino\",\n  \"date\": \"2015-05-28T22:40:32.169Z\",\n  \"description\": \"This is a custom description for SEO and Open Graph purposes, rather than the default generated excerpt. Simply add a description field to the frontmatter.\",\n  \"featuredImage\": \"./grassland-by-qingbao-meng.jpg\"\n};\n\nvar makeShortcode = function makeShortcode(name) {\n  return function MDXDefaultShortcode(props) {\n    console.warn(\"Component \" + name + \" was not imported, exported, or provided by MDXProvider as global scope\");\n    return mdx(\"div\", props);\n  };\n};\n\nvar Blockquote = makeShortcode(\"Blockquote\");\nvar Video = makeShortcode(\"Video\");\nvar layoutProps = {\n  _frontmatter: _frontmatter\n};\nvar MDXLayout = \"wrapper\";\nreturn function MDXContent(_ref) {\n  var components = _ref.components,\n      props = _objectWithoutProperties(_ref, [\"components\"]);\n\n  return mdx(MDXLayout, _extends({}, layoutProps, props, {\n    components: components,\n    mdxType: \"MDXLayout\"\n  }), mdx(\"h1\", null, \"Images\"), mdx(\"p\", null, \"Images with captions\"), mdx(\"figure\", null, mdx(\"p\", null, mdx(\"span\", _extends({\n    parentName: \"p\"\n  }, {\n    \"className\": \"gatsby-resp-image-wrapper\",\n    \"style\": {\n      \"position\": \"relative\",\n      \"display\": \"block\",\n      \"marginLeft\": \"auto\",\n      \"marginRight\": \"auto\",\n      \"maxWidth\": \"1920px\"\n    }\n  }), \"\\n      \", mdx(\"a\", _extends({\n    parentName: \"span\"\n  }, {\n    \"className\": \"gatsby-resp-image-link\",\n    \"href\": \"/static/44c8aaab64636b59604768558df10f76/9c49d/nature-valley-by-redcharlie.jpg\",\n    \"style\": {\n      \"display\": \"block\"\n    },\n    \"target\": \"_blank\",\n    \"rel\": [\"noopener\"]\n  }), \"\\n    \", mdx(\"span\", _extends({\n    parentName: \"a\"\n  }, {\n    \"className\": \"gatsby-resp-image-background-image\",\n    \"style\": {\n      \"paddingBottom\": \"66.66666666666666%\",\n      \"position\": \"relative\",\n      \"bottom\": \"0\",\n      \"left\": \"0\",\n      \"backgroundImage\": \"url('data:image/jpeg;base64,/9j/2wBDABALDA4MChAODQ4SERATGCgaGBYWGDEjJR0oOjM9PDkzODdASFxOQERXRTc4UG1RV19iZ2hnPk1xeXBkeFxlZ2P/2wBDARESEhgVGC8aGi9jQjhCY2NjY2NjY2NjY2NjY2NjY2NjY2NjY2NjY2NjY2NjY2NjY2NjY2NjY2NjY2NjY2NjY2P/wgARCAANABQDASIAAhEBAxEB/8QAFwAAAwEAAAAAAAAAAAAAAAAAAAMEAf/EABcBAAMBAAAAAAAAAAAAAAAAAAABAgP/2gAMAwEAAhADEAAAAdhiblTRIz//xAAZEAEBAQEBAQAAAAAAAAAAAAABAAIDERP/2gAIAQEAAQUCex2y5lb2+jOkv//EABURAQEAAAAAAAAAAAAAAAAAABAR/9oACAEDAQE/Aaf/xAAWEQEBAQAAAAAAAAAAAAAAAAAAEQH/2gAIAQIBAT8Bmo//xAAYEAEAAwEAAAAAAAAAAAAAAAABACAiQf/aAAgBAQAGPwLgzKlf/8QAGhAAAwEBAQEAAAAAAAAAAAAAAAERIUExUf/aAAgBAQABPyF1c6xabed3KKNSyfTwKO7CJIf/2gAMAwEAAgADAAAAEHwP/8QAFxEAAwEAAAAAAAAAAAAAAAAAAAERQf/aAAgBAwEBPxCHhT//xAAWEQEBAQAAAAAAAAAAAAAAAAABABH/2gAIAQIBAT8QSdG1f//EAB0QAQEAAgIDAQAAAAAAAAAAAAERADEhYVFxkdH/2gAIAQEAAT8QZDrwtfZ3j2ApPg+ec2Rgw06wqZoy1YeRf3HAJl1n/9k=')\",\n      \"backgroundSize\": \"cover\",\n      \"display\": \"block\"\n    }\n  })), \"\\n  \", mdx(\"img\", _extends({\n    parentName: \"a\"\n  }, {\n    \"className\": \"gatsby-resp-image-image\",\n    \"alt\": \"Photo by redcharlie on Unsplash\",\n    \"title\": \"Photo by redcharlie on Unsplash\",\n    \"src\": \"/static/44c8aaab64636b59604768558df10f76/fb329/nature-valley-by-redcharlie.jpg\",\n    \"srcSet\": [\"/static/44c8aaab64636b59604768558df10f76/98431/nature-valley-by-redcharlie.jpg 480w\", \"/static/44c8aaab64636b59604768558df10f76/b3ee8/nature-valley-by-redcharlie.jpg 960w\", \"/static/44c8aaab64636b59604768558df10f76/fb329/nature-valley-by-redcharlie.jpg 1920w\", \"/static/44c8aaab64636b59604768558df10f76/9c49d/nature-valley-by-redcharlie.jpg 1950w\"],\n    \"sizes\": \"(max-width: 1920px) 100vw, 1920px\",\n    \"loading\": \"lazy\"\n  })), \"\\n  \"), \"\\n    \"))), mdx(\"p\", null, \"Use markdown in the image caption if you want!\"), mdx(\"p\", null, mdx(\"span\", _extends({\n    parentName: \"p\"\n  }, {\n    \"className\": \"gatsby-resp-image-wrapper\",\n    \"style\": {\n      \"position\": \"relative\",\n      \"display\": \"block\",\n      \"marginLeft\": \"auto\",\n      \"marginRight\": \"auto\",\n      \"maxWidth\": \"1920px\"\n    }\n  }), \"\\n      \", mdx(\"a\", _extends({\n    parentName: \"span\"\n  }, {\n    \"className\": \"gatsby-resp-image-link\",\n    \"href\": \"/static/21a7d34d97e7f39ac44cc649a2bd85f2/9c49d/cloudy-day-by-riccardo-chiarini.jpg\",\n    \"style\": {\n      \"display\": \"block\"\n    },\n    \"target\": \"_blank\",\n    \"rel\": [\"noopener\"]\n  }), \"\\n    \", mdx(\"span\", _extends({\n    parentName: \"a\"\n  }, {\n    \"className\": \"gatsby-resp-image-background-image\",\n    \"style\": {\n      \"paddingBottom\": \"66.66666666666666%\",\n      \"position\": \"relative\",\n      \"bottom\": \"0\",\n      \"left\": \"0\",\n      \"backgroundImage\": \"url('data:image/jpeg;base64,/9j/2wBDABALDA4MChAODQ4SERATGCgaGBYWGDEjJR0oOjM9PDkzODdASFxOQERXRTc4UG1RV19iZ2hnPk1xeXBkeFxlZ2P/2wBDARESEhgVGC8aGi9jQjhCY2NjY2NjY2NjY2NjY2NjY2NjY2NjY2NjY2NjY2NjY2NjY2NjY2NjY2NjY2NjY2NjY2P/wgARCAANABQDASIAAhEBAxEB/8QAFgABAQEAAAAAAAAAAAAAAAAAAwQA/8QAFgEBAQEAAAAAAAAAAAAAAAAAAAEC/9oADAMBAAIQAxAAAAGgRHKrS6P/xAAbEAABBQEBAAAAAAAAAAAAAAACAAEREhMDMf/aAAgBAQABBQJzONjnXsvRo01Zf//EABURAQEAAAAAAAAAAAAAAAAAABAR/9oACAEDAQE/Aaf/xAAWEQADAAAAAAAAAAAAAAAAAAABEBH/2gAIAQIBAT8BFX//xAAZEAADAAMAAAAAAAAAAAAAAAAAATECEDL/2gAIAQEABj8CjOciFe//xAAbEAADAAMBAQAAAAAAAAAAAAAAAREhMWFRgf/aAAgBAQABPyFq4cg8BO+i2pslfE9KpjYpH//aAAwDAQACAAMAAAAQI/8A/8QAGBEAAwEBAAAAAAAAAAAAAAAAAAEhEVH/2gAIAQMBAT8QbbEXh//EABgRAAIDAAAAAAAAAAAAAAAAAAABIUFR/9oACAECAQE/EEsydP/EABsQAQADAAMBAAAAAAAAAAAAAAEAESExQXGh/9oACAEBAAE/EGoMA0A+QVlAuygszXn2CN4DG0ULrlsZ2oaNn//Z')\",\n      \"backgroundSize\": \"cover\",\n      \"display\": \"block\"\n    }\n  })), \"\\n  \", mdx(\"img\", _extends({\n    parentName: \"a\"\n  }, {\n    \"className\": \"gatsby-resp-image-image\",\n    \"alt\": \"Photo by Riccardo Chiarini on Unsplash\",\n    \"title\": \"Photo by Riccardo Chiarini on Unsplash\",\n    \"src\": \"/static/21a7d34d97e7f39ac44cc649a2bd85f2/fb329/cloudy-day-by-riccardo-chiarini.jpg\",\n    \"srcSet\": [\"/static/21a7d34d97e7f39ac44cc649a2bd85f2/98431/cloudy-day-by-riccardo-chiarini.jpg 480w\", \"/static/21a7d34d97e7f39ac44cc649a2bd85f2/b3ee8/cloudy-day-by-riccardo-chiarini.jpg 960w\", \"/static/21a7d34d97e7f39ac44cc649a2bd85f2/fb329/cloudy-day-by-riccardo-chiarini.jpg 1920w\", \"/static/21a7d34d97e7f39ac44cc649a2bd85f2/9c49d/cloudy-day-by-riccardo-chiarini.jpg 1950w\"],\n    \"sizes\": \"(max-width: 1920px) 100vw, 1920px\",\n    \"loading\": \"lazy\"\n  })), \"\\n  \"), \"\\n    \")), mdx(\"h1\", null, \"This is an H1\"), mdx(\"p\", null, \"Quisque facilisis erat a dui. Nam malesuada ornare dolor. Cras gravida, diam sit amet rhoncus ornare, erat elit consectetuer erat, id egestas pede nibh eget odio. Proin tincidunt, velit vel porta elementum, magna diam molestie sapien, non aliquet massa pede eu diam. Aliquam iaculis. Fusce et ipsum et nulla tristique facilisis.\"), mdx(\"h2\", null, \"This is an H2\"), mdx(\"p\", null, \"Lorem ipsum dolor sit amet, consectetuer adipiscing elit. Morbi commodo, ipsum sed pharetra gravida, orci magna rhoncus neque, id pulvinar odio lorem non turpis. Nullam sit amet enim. Suspendisse id velit vitae ligula volutpat condimentum. Aliquam erat volutpat. Sed quis velit. Nulla facilisi. Nulla libero.\"), mdx(\"h3\", null, \"This is an H3\"), mdx(\"p\", null, \"Lorem ipsum dolor sit amet, consectetuer adipiscing elit. Morbi commodo, ipsum sed pharetra gravida, orci magna rhoncus neque, id pulvinar odio lorem non turpis. Nullam sit amet enim. Suspendisse id velit vitae ligula volutpat condimentum. Aliquam erat volutpat. Sed quis velit. Nulla facilisi. Nulla libero.\"), mdx(\"h4\", null, \"This is an H4\"), mdx(\"p\", null, \"Quisque facilisis erat a dui. Nam malesuada ornare dolor. Cras gravida, diam sit amet rhoncus ornare, erat elit consectetuer erat, id egestas pede nibh eget odio. Proin tincidunt, velit vel porta elementum, magna diam molestie sapien, non aliquet massa pede eu diam. Aliquam iaculis.\"), mdx(\"h2\", null, \"Quotes\"), mdx(Blockquote, {\n    by: \"Scott Adams\",\n    mdxType: \"Blockquote\"\n  }, \"Creativity is allowing yourself to make mistakes. Design is knowing which ones to keep.\"), mdx(\"h2\", null, \"Code\"), mdx(\"pre\", null, mdx(\"code\", _extends({\n    parentName: \"pre\"\n  }, {}), \"// Simple map\\nvar map;\\nfunction initMap() {\\n  map = new google.maps.Map(document.getElementById('map'), {\\n    center: {lat: -34.397, lng: 150.644},\\n    zoom: 8\\n  });\\n}\\n\")), mdx(\"h2\", null, \"Lists\"), mdx(\"h3\", null, \"Unordered Lists\"), mdx(\"p\", null, \"The HTML \", mdx(\"inlineCode\", {\n    parentName: \"p\"\n  }, \"<ul>\"), \" element represents an unordered list of items, typically rendered as a bulleted list.\"), mdx(\"p\", null, \"Usage notes:\"), mdx(\"ul\", null, mdx(\"li\", {\n    parentName: \"ul\"\n  }, \"The \", mdx(\"inlineCode\", {\n    parentName: \"li\"\n  }, \"<ul>\"), \" element is for grouping a collection of items that do not have a numerical ordering, and their order in the list is meaningless. Typically, unordered-list items are displayed with a bullet, which can be of several forms, like a dot, a circle or a squared.\"), mdx(\"li\", {\n    parentName: \"ul\"\n  }, \"There is no limitation to the depth and alternation of nested lists defined with the \", mdx(\"inlineCode\", {\n    parentName: \"li\"\n  }, \"<ol>\"), \" and \", mdx(\"inlineCode\", {\n    parentName: \"li\"\n  }, \"<ul>\"), \" elements.\"), mdx(\"li\", {\n    parentName: \"ul\"\n  }, \"The \", mdx(\"inlineCode\", {\n    parentName: \"li\"\n  }, \"<ol>\"), \" and \", mdx(\"inlineCode\", {\n    parentName: \"li\"\n  }, \"<ul>\"), \" elements both represent a list of items. They differ in that, with the \", mdx(\"inlineCode\", {\n    parentName: \"li\"\n  }, \"<ol>\"), \" element, the order is meaningful.\")), mdx(\"h3\", null, \"Ordered Lists\"), mdx(\"p\", null, \"The HTML \", mdx(\"inlineCode\", {\n    parentName: \"p\"\n  }, \"<ol>\"), \" element represents an ordered list of items, typically rendered as a numbered list.\"), mdx(\"p\", null, \"Usage notes:\"), mdx(\"ol\", null, mdx(\"li\", {\n    parentName: \"ol\"\n  }, \"Typically, ordered-list items are displayed with a preceding numbering, which can be of any form, like numerals, letters or Romans numerals or even simple bullets.\"), mdx(\"li\", {\n    parentName: \"ol\"\n  }, \"There is no limitation to the depth and alternation of nested lists defined with the \", mdx(\"inlineCode\", {\n    parentName: \"li\"\n  }, \"<ol>\"), \" and \", mdx(\"inlineCode\", {\n    parentName: \"li\"\n  }, \"<ul>\"), \" elements.\"), mdx(\"li\", {\n    parentName: \"ol\"\n  }, \"The \", mdx(\"inlineCode\", {\n    parentName: \"li\"\n  }, \"<ol>\"), \" and \", mdx(\"inlineCode\", {\n    parentName: \"li\"\n  }, \"<ul>\"), \" both represent a list of items. They differ in the way that, with the \", mdx(\"inlineCode\", {\n    parentName: \"li\"\n  }, \"<ol>\"), \" element, the order is meaningful.\")), mdx(\"h2\", null, \"Videos\"), mdx(Video, {\n    url: \"https://www.youtube.com/watch?v=lC5lsemxaJo\",\n    mdxType: \"Video\"\n  }));\n}\n;\nMDXContent.isMDXComponent = true;","rawMDXOutput":"/* @jsx mdx */\nimport { mdx } from '@mdx-js/react';\n/* @jsx mdx */\n\nexport const _frontmatter = {\n  \"title\": \"Testerino\",\n  \"date\": \"2015-05-28T22:40:32.169Z\",\n  \"description\": \"This is a custom description for SEO and Open Graph purposes, rather than the default generated excerpt. Simply add a description field to the frontmatter.\",\n  \"featuredImage\": \"./grassland-by-qingbao-meng.jpg\"\n};\nconst makeShortcode = name => function MDXDefaultShortcode(props) {\n  console.warn(\"Component \" + name + \" was not imported, exported, or provided by MDXProvider as global scope\")\n  return <div {...props}/>\n};\nconst Blockquote = makeShortcode(\"Blockquote\");\nconst Video = makeShortcode(\"Video\");\nconst layoutProps = {\n  _frontmatter\n};\nconst MDXLayout = \"wrapper\"\nexport default function MDXContent({\n  components,\n  ...props\n}) {\n  return <MDXLayout {...layoutProps} {...props} components={components} mdxType=\"MDXLayout\">\n    <h1>{`Images`}</h1>\n    <p>{`Images with captions`}</p>\n    <figure>\n      <p><span parentName=\"p\" {...{\n          \"className\": \"gatsby-resp-image-wrapper\",\n          \"style\": {\n            \"position\": \"relative\",\n            \"display\": \"block\",\n            \"marginLeft\": \"auto\",\n            \"marginRight\": \"auto\",\n            \"maxWidth\": \"1920px\"\n          }\n        }}>{`\n      `}<a parentName=\"span\" {...{\n            \"className\": \"gatsby-resp-image-link\",\n            \"href\": \"/static/44c8aaab64636b59604768558df10f76/9c49d/nature-valley-by-redcharlie.jpg\",\n            \"style\": {\n              \"display\": \"block\"\n            },\n            \"target\": \"_blank\",\n            \"rel\": [\"noopener\"]\n          }}>{`\n    `}<span parentName=\"a\" {...{\n              \"className\": \"gatsby-resp-image-background-image\",\n              \"style\": {\n                \"paddingBottom\": \"66.66666666666666%\",\n                \"position\": \"relative\",\n                \"bottom\": \"0\",\n                \"left\": \"0\",\n                \"backgroundImage\": \"url('data:image/jpeg;base64,/9j/2wBDABALDA4MChAODQ4SERATGCgaGBYWGDEjJR0oOjM9PDkzODdASFxOQERXRTc4UG1RV19iZ2hnPk1xeXBkeFxlZ2P/2wBDARESEhgVGC8aGi9jQjhCY2NjY2NjY2NjY2NjY2NjY2NjY2NjY2NjY2NjY2NjY2NjY2NjY2NjY2NjY2NjY2NjY2P/wgARCAANABQDASIAAhEBAxEB/8QAFwAAAwEAAAAAAAAAAAAAAAAAAAMEAf/EABcBAAMBAAAAAAAAAAAAAAAAAAABAgP/2gAMAwEAAhADEAAAAdhiblTRIz//xAAZEAEBAQEBAQAAAAAAAAAAAAABAAIDERP/2gAIAQEAAQUCex2y5lb2+jOkv//EABURAQEAAAAAAAAAAAAAAAAAABAR/9oACAEDAQE/Aaf/xAAWEQEBAQAAAAAAAAAAAAAAAAAAEQH/2gAIAQIBAT8Bmo//xAAYEAEAAwEAAAAAAAAAAAAAAAABACAiQf/aAAgBAQAGPwLgzKlf/8QAGhAAAwEBAQEAAAAAAAAAAAAAAAERIUExUf/aAAgBAQABPyF1c6xabed3KKNSyfTwKO7CJIf/2gAMAwEAAgADAAAAEHwP/8QAFxEAAwEAAAAAAAAAAAAAAAAAAAERQf/aAAgBAwEBPxCHhT//xAAWEQEBAQAAAAAAAAAAAAAAAAABABH/2gAIAQIBAT8QSdG1f//EAB0QAQEAAgIDAQAAAAAAAAAAAAERADEhYVFxkdH/2gAIAQEAAT8QZDrwtfZ3j2ApPg+ec2Rgw06wqZoy1YeRf3HAJl1n/9k=')\",\n                \"backgroundSize\": \"cover\",\n                \"display\": \"block\"\n              }\n            }}></span>{`\n  `}<img parentName=\"a\" {...{\n              \"className\": \"gatsby-resp-image-image\",\n              \"alt\": \"Photo by redcharlie on Unsplash\",\n              \"title\": \"Photo by redcharlie on Unsplash\",\n              \"src\": \"/static/44c8aaab64636b59604768558df10f76/fb329/nature-valley-by-redcharlie.jpg\",\n              \"srcSet\": [\"/static/44c8aaab64636b59604768558df10f76/98431/nature-valley-by-redcharlie.jpg 480w\", \"/static/44c8aaab64636b59604768558df10f76/b3ee8/nature-valley-by-redcharlie.jpg 960w\", \"/static/44c8aaab64636b59604768558df10f76/fb329/nature-valley-by-redcharlie.jpg 1920w\", \"/static/44c8aaab64636b59604768558df10f76/9c49d/nature-valley-by-redcharlie.jpg 1950w\"],\n              \"sizes\": \"(max-width: 1920px) 100vw, 1920px\",\n              \"loading\": \"lazy\"\n            }}></img>{`\n  `}</a>{`\n    `}</span></p>\n    </figure>\n    <p>{`Use markdown in the image caption if you want!`}</p>\n    <p><span parentName=\"p\" {...{\n        \"className\": \"gatsby-resp-image-wrapper\",\n        \"style\": {\n          \"position\": \"relative\",\n          \"display\": \"block\",\n          \"marginLeft\": \"auto\",\n          \"marginRight\": \"auto\",\n          \"maxWidth\": \"1920px\"\n        }\n      }}>{`\n      `}<a parentName=\"span\" {...{\n          \"className\": \"gatsby-resp-image-link\",\n          \"href\": \"/static/21a7d34d97e7f39ac44cc649a2bd85f2/9c49d/cloudy-day-by-riccardo-chiarini.jpg\",\n          \"style\": {\n            \"display\": \"block\"\n          },\n          \"target\": \"_blank\",\n          \"rel\": [\"noopener\"]\n        }}>{`\n    `}<span parentName=\"a\" {...{\n            \"className\": \"gatsby-resp-image-background-image\",\n            \"style\": {\n              \"paddingBottom\": \"66.66666666666666%\",\n              \"position\": \"relative\",\n              \"bottom\": \"0\",\n              \"left\": \"0\",\n              \"backgroundImage\": \"url('data:image/jpeg;base64,/9j/2wBDABALDA4MChAODQ4SERATGCgaGBYWGDEjJR0oOjM9PDkzODdASFxOQERXRTc4UG1RV19iZ2hnPk1xeXBkeFxlZ2P/2wBDARESEhgVGC8aGi9jQjhCY2NjY2NjY2NjY2NjY2NjY2NjY2NjY2NjY2NjY2NjY2NjY2NjY2NjY2NjY2NjY2NjY2P/wgARCAANABQDASIAAhEBAxEB/8QAFgABAQEAAAAAAAAAAAAAAAAAAwQA/8QAFgEBAQEAAAAAAAAAAAAAAAAAAAEC/9oADAMBAAIQAxAAAAGgRHKrS6P/xAAbEAABBQEBAAAAAAAAAAAAAAACAAEREhMDMf/aAAgBAQABBQJzONjnXsvRo01Zf//EABURAQEAAAAAAAAAAAAAAAAAABAR/9oACAEDAQE/Aaf/xAAWEQADAAAAAAAAAAAAAAAAAAABEBH/2gAIAQIBAT8BFX//xAAZEAADAAMAAAAAAAAAAAAAAAAAATECEDL/2gAIAQEABj8CjOciFe//xAAbEAADAAMBAQAAAAAAAAAAAAAAAREhMWFRgf/aAAgBAQABPyFq4cg8BO+i2pslfE9KpjYpH//aAAwDAQACAAMAAAAQI/8A/8QAGBEAAwEBAAAAAAAAAAAAAAAAAAEhEVH/2gAIAQMBAT8QbbEXh//EABgRAAIDAAAAAAAAAAAAAAAAAAABIUFR/9oACAECAQE/EEsydP/EABsQAQADAAMBAAAAAAAAAAAAAAEAESExQXGh/9oACAEBAAE/EGoMA0A+QVlAuygszXn2CN4DG0ULrlsZ2oaNn//Z')\",\n              \"backgroundSize\": \"cover\",\n              \"display\": \"block\"\n            }\n          }}></span>{`\n  `}<img parentName=\"a\" {...{\n            \"className\": \"gatsby-resp-image-image\",\n            \"alt\": \"Photo by Riccardo Chiarini on Unsplash\",\n            \"title\": \"Photo by Riccardo Chiarini on Unsplash\",\n            \"src\": \"/static/21a7d34d97e7f39ac44cc649a2bd85f2/fb329/cloudy-day-by-riccardo-chiarini.jpg\",\n            \"srcSet\": [\"/static/21a7d34d97e7f39ac44cc649a2bd85f2/98431/cloudy-day-by-riccardo-chiarini.jpg 480w\", \"/static/21a7d34d97e7f39ac44cc649a2bd85f2/b3ee8/cloudy-day-by-riccardo-chiarini.jpg 960w\", \"/static/21a7d34d97e7f39ac44cc649a2bd85f2/fb329/cloudy-day-by-riccardo-chiarini.jpg 1920w\", \"/static/21a7d34d97e7f39ac44cc649a2bd85f2/9c49d/cloudy-day-by-riccardo-chiarini.jpg 1950w\"],\n            \"sizes\": \"(max-width: 1920px) 100vw, 1920px\",\n            \"loading\": \"lazy\"\n          }}></img>{`\n  `}</a>{`\n    `}</span></p>\n    <h1>{`This is an H1`}</h1>\n    <p>{`Quisque facilisis erat a dui. Nam malesuada ornare dolor. Cras gravida, diam sit amet rhoncus ornare, erat elit consectetuer erat, id egestas pede nibh eget odio. Proin tincidunt, velit vel porta elementum, magna diam molestie sapien, non aliquet massa pede eu diam. Aliquam iaculis. Fusce et ipsum et nulla tristique facilisis.`}</p>\n    <h2>{`This is an H2`}</h2>\n    <p>{`Lorem ipsum dolor sit amet, consectetuer adipiscing elit. Morbi commodo, ipsum sed pharetra gravida, orci magna rhoncus neque, id pulvinar odio lorem non turpis. Nullam sit amet enim. Suspendisse id velit vitae ligula volutpat condimentum. Aliquam erat volutpat. Sed quis velit. Nulla facilisi. Nulla libero.`}</p>\n    <h3>{`This is an H3`}</h3>\n    <p>{`Lorem ipsum dolor sit amet, consectetuer adipiscing elit. Morbi commodo, ipsum sed pharetra gravida, orci magna rhoncus neque, id pulvinar odio lorem non turpis. Nullam sit amet enim. Suspendisse id velit vitae ligula volutpat condimentum. Aliquam erat volutpat. Sed quis velit. Nulla facilisi. Nulla libero.`}</p>\n    <h4>{`This is an H4`}</h4>\n    <p>{`Quisque facilisis erat a dui. Nam malesuada ornare dolor. Cras gravida, diam sit amet rhoncus ornare, erat elit consectetuer erat, id egestas pede nibh eget odio. Proin tincidunt, velit vel porta elementum, magna diam molestie sapien, non aliquet massa pede eu diam. Aliquam iaculis.`}</p>\n    <h2>{`Quotes`}</h2>\n    <Blockquote by=\"Scott Adams\" mdxType=\"Blockquote\">\n  Creativity is allowing yourself to make mistakes. Design is knowing which ones\n  to keep.\n    </Blockquote>\n    <h2>{`Code`}</h2>\n    <pre><code parentName=\"pre\" {...{}}>{`// Simple map\nvar map;\nfunction initMap() {\n  map = new google.maps.Map(document.getElementById('map'), {\n    center: {lat: -34.397, lng: 150.644},\n    zoom: 8\n  });\n}\n`}</code></pre>\n    <h2>{`Lists`}</h2>\n    <h3>{`Unordered Lists`}</h3>\n    <p>{`The HTML `}<inlineCode parentName=\"p\">{`<ul>`}</inlineCode>{` element represents an unordered list of items, typically rendered as a bulleted list.`}</p>\n    <p>{`Usage notes:`}</p>\n    <ul>\n      <li parentName=\"ul\">{`The `}<inlineCode parentName=\"li\">{`<ul>`}</inlineCode>{` element is for grouping a collection of items that do not have a numerical ordering, and their order in the list is meaningless. Typically, unordered-list items are displayed with a bullet, which can be of several forms, like a dot, a circle or a squared.`}</li>\n      <li parentName=\"ul\">{`There is no limitation to the depth and alternation of nested lists defined with the `}<inlineCode parentName=\"li\">{`<ol>`}</inlineCode>{` and `}<inlineCode parentName=\"li\">{`<ul>`}</inlineCode>{` elements.`}</li>\n      <li parentName=\"ul\">{`The `}<inlineCode parentName=\"li\">{`<ol>`}</inlineCode>{` and `}<inlineCode parentName=\"li\">{`<ul>`}</inlineCode>{` elements both represent a list of items. They differ in that, with the `}<inlineCode parentName=\"li\">{`<ol>`}</inlineCode>{` element, the order is meaningful.`}</li>\n    </ul>\n    <h3>{`Ordered Lists`}</h3>\n    <p>{`The HTML `}<inlineCode parentName=\"p\">{`<ol>`}</inlineCode>{` element represents an ordered list of items, typically rendered as a numbered list.`}</p>\n    <p>{`Usage notes:`}</p>\n    <ol>\n      <li parentName=\"ol\">{`Typically, ordered-list items are displayed with a preceding numbering, which can be of any form, like numerals, letters or Romans numerals or even simple bullets.`}</li>\n      <li parentName=\"ol\">{`There is no limitation to the depth and alternation of nested lists defined with the `}<inlineCode parentName=\"li\">{`<ol>`}</inlineCode>{` and `}<inlineCode parentName=\"li\">{`<ul>`}</inlineCode>{` elements.`}</li>\n      <li parentName=\"ol\">{`The `}<inlineCode parentName=\"li\">{`<ol>`}</inlineCode>{` and `}<inlineCode parentName=\"li\">{`<ul>`}</inlineCode>{` both represent a list of items. They differ in the way that, with the `}<inlineCode parentName=\"li\">{`<ol>`}</inlineCode>{` element, the order is meaningful.`}</li>\n    </ol>\n    <h2>{`Videos`}</h2>\n    <Video url=\"https://www.youtube.com/watch?v=lC5lsemxaJo\" mdxType=\"Video\" />\n\n    </MDXLayout>;\n}\n\n;\nMDXContent.isMDXComponent = true;"}}